Workbook

Sheet P&L Summary
A1: DEALERSHIP GROUP — P&L SUMMARY 2026
A2: Line Item | B2: Jan | C2: Feb | D2: Mar | E2: Apr | F2: May | G2: Jun | H2: Jul | I2: Aug | J2: Sep | K2: Oct | L2: Nov | M2: Dec | N2: YTD | O2: Budget | P2: Variance
A4: New Vehicle Sales | B4: 902143 | C4: 814579 | D4: 885162 | E4: 870939 | F4: 813920 | G4: 842700 | H4: 899872 | I4: 725339 | J4: 764040 | K4: 751025 | L4: 906636 | M4: 841427 | N4: =SUM(B4:M4) -> 10017782
A5: Used Vehicle Sales | B5: 412264 | C5: 447838 | D5: 393554 | E5: 381882 | F5: 393634 | G5: 434006 | H5: 432379 | I5: 375930 | J5: 453938 | K5: 419982 | L5: 423634 | M5: 433301 | N5: =SUM(B5:M5) -> 5002342
A6: F&I Income | B6: 90603 | C6: 93668 | D6: 84541 | E6: 78353 | F6: 85856 | G6: 90509 | H6: 82321 | I6: 92593 | J6: 89501 | K6: 86022 | L6: 98684 | M6: 89941 | N6: =SUM(B6:M6) -> 1062592
A7: Service Revenue | B7: 197716 | C7: 185338 | D7: 163702 | E7: 201575 | F7: 164732 | G7: 179977 | H7: 179374 | I7: 195980 | J7: 178654 | K7: 165799 | L7: 173505 | M7: 191975 | N7: =SUM(B7:M7) -> 2178327
A8: Parts Revenue | B8: 85963 | C8: 96867 | D8: 100852 | E8: 86641 | F8: 91632 | G8: 91318 | H8: 98255 | I8: 102532 | J8: 99210 | K8: 105962 | L8: 94510 | M8: 87755 | N8: =SUM(B8:M8) -> 1141497
A9: Body Shop Revenue | B9: 38319 | C9: 44177 | D9: 46471 | E9: 37332 | F9: 38992 | G9: 44934 | H9: 45888 | I9: 40141 | J9: 40085 | K9: 40974 | L9: 45179 | M9: 41731 | N9: =SUM(B9:M9) -> 504223
A11: Total Revenue | B11: =SUM(B4:B10) -> 1727008 | C11: =SUM(C4:C10) -> 1682467 | D11: =SUM(D4:D10) -> 1674282 | E11: =SUM(E4:E10) -> 1656722 | F11: =SUM(F4:F10) -> 1588766 | G11: =SUM(G4:G10) -> 1683444 | H11: =SUM(H4:H10) -> 1738089 | I11: =SUM(I4:I10) -> 1532515 | ... M11: =SUM(M4:M10) -> 1686130
A13: New Vehicle Gross | B13: 127425 | C13: 154522 | D13: ='New Vehicle'!$B$45 -> 81057.72 | E13: 138503 | F13: 164078 | G13: 127922 | H13: 154914 | I13: 137930 | J13: 161290 | K13: 145200 | L13: 143560 | M13: 145324
A14: Used Vehicle Gross | B14: 127906 | C14: 107067 | D14: ='Used Vehicle'!$B$36 -> 30811.994 | E14: 101930 | F14: 118982 | G14: 108022 | H14: 122533 | I14: 104626 | J14: 98413 | K14: 109951 | L14: 110157 | M14: 129209
A15: F&I Gross | B15: 80468 | C15: 83493 | D15: ='F&I Detail'!$B$86 -> 40457 | E15: 78389 | F15: 84405 | G15: 83543 | H15: 87555 | I15: 94811 | J15: 80099 | K15: 87502 | L15: 87588 | M15: 95055
A16: Service & Parts Gross | B16: 155040 | C16: 142754 | D16: ='Service & Parts'!$B$175 -> 31642 | E16: 135306 | F16: 143774 | G16: 150067 | H16: 119674 | I16: 145087 | J16: 134117 | K16: 138541 | L16: 148345 | M16: 123923
A18: Total Gross Profit | B18: =SUM(B13:B16) -> 490839 | C18: =SUM(C13:C16) -> 487836 | D18: =SUM(D13:D16) -> 183968.71 | E18: =SUM(E13:E16) -> 454128 | F18: =SUM(F13:F16) -> 511239 | G18: =SUM(G13:G16) -> 469554 | H18: =SUM(H13:H16) -> 484676 | I18: =SUM(I13:I16) -> 482454 | ... M18: =SUM(M13:M16) -> 493511 | O18: 510000 | P18: =D18-O18 -> -326031.29
A20: Personnel Cost | B20: 166496 | C20: 190041 | D20: 185128 | E20: 178219 | F20: 169235 | G20: 172396 | H20: 184180 | I20: 176029 | J20: 192944 | K20: 166532 | L20: 170019 | M20: 178557
A21: Facilities & Utilities | B21: 53864 | C21: 54506 | D21: 51276 | E21: 51811 | F21: 53829 | G21: 53366 | H21: 53052 | I21: 59052 | J21: 50828 | K21: 52237 | L21: 55156 | M21: 58639
A22: Advertising | B22: 26287 | C22: 29231 | D22: 28914 | E22: 26721 | F22: 28501 | G22: 28869 | H22: 30233 | I22: 26656 | J22: 26368 | K22: 26091 | L22: 26533 | M22: 28955
A23: Other Opex | B23: 23750 | C23: 23093 | D23: 23645 | E23: 23712 | F23: 22590 | G23: 22737 | H23: 22175 | I23: 21262 | J23: 21295 | K23: 20794 | L23: 22737 | M23: 22704
A24: Depreciation | B24: 17061 | C24: 17601 | D24: 17205 | E24: 19397 | F24: 18841 | G24: 17241 | H24: 17982 | I24: 17599 | J24: 18208 | K24: 17906 | L24: 19391 | M24: 16933
A25: Total Operating Expenses | B25: =SUM(B20:B24) -> 287458 | C25: =SUM(C20:C24) -> 314472 | D25: =SUM(D20:D24) -> 306168 | E25: =SUM(E20:E24) -> 299860 | F25: =SUM(F20:F24) -> 292996 | G25: =SUM(G20:G24) -> 294609 | H25: =SUM(H20:H24) -> 307622 | I25: =SUM(I20:I24) -> 300598 | ... M25: =SUM(M20:M24) -> 305788
A26: Operating Income (EBIT) | B26: =B18-B25 -> 203381 | C26: =C18-C25 -> 173364 | D26: =D18-D25 -> -122199.29 | E26: =E18-E25 -> 154268 | F26: =F18-F25 -> 218243 | G26: =G18-G25 -> 174945 | H26: =H18-H25 -> 177054 | I26: =I18-I25 -> 181856 | ... M26: =M18-M25 -> 187723
A27: D&A Addback | B27: =B24 -> 17061 | C27: =C24 -> 17601 | D27: =D24 -> 17205 | E27: =E24 -> 19397 | F27: =F24 -> 18841 | G27: =G24 -> 17241 | H27: =H24 -> 17982 | I27: =I24 -> 17599 | ... M27: =M24 -> 16933
A28: Owner Comp Addback | B28: =OwnerCompAddback -> 8000 | C28: =OwnerCompAddback -> 8000 | D28: =OwnerCompAddback -> 8000 | E28: =OwnerCompAddback -> 8000 | F28: =OwnerCompAddback -> 8000 | G28: =OwnerCompAddback -> 8000 | H28: =OwnerCompAddback -> 8000 | I28: =OwnerCompAddback -> 8000 | ... M28: =OwnerCompAddback -> 8000
A29: One-Time Legal Addback | B29: =LegalCostAddback -> 5000 | C29: =LegalCostAddback -> 5000 | D29: =LegalCostAddback -> 5000 | E29: =LegalCostAddback -> 5000 | F29: =LegalCostAddback -> 5000 | G29: =LegalCostAddback -> 5000 | H29: =LegalCostAddback -> 5000 | I29: =LegalCostAddback -> 5000 | ... M29: =LegalCostAddback -> 5000
A30: Interest Expense | B30: 2706 | C30: 2538 | D30: 4533 | E30: 5261 | F30: 7873 | G30: 7888 | H30: 5921 | I30: 6306 | J30: 5365 | K30: 5354 | L30: 6709 | M30: 2604
A31: Other Addback | B31: 3026 | C31: 4597 | D31: 7262 | E31: 2607 | F31: 5686 | G31: 5816 | H31: 7571 | I31: 6238 | J31: 4822 | K31: 3051 | L31: 6516 | M31: 7241
A32: Adjusted EBITDA | B32: =B18-B25+B27+B28+B29+B31 -> 236468 | C32: =C18-C25+C27+C28+C29+C31 -> 208562 | D32: =D18-D25+D27+D28+D29+D31 -> -84732.286 | E32: =E18-E25+E27+E28+E29+E31 -> 189272 | F32: =F18-F25+F27+F28+F29+F31 -> 255770 | G32: =G18-G25+G27+G28+G29+G31 -> 211002 | H32: =H18-H25+H27+H28+H29+H31 -> 215607 | I32: =I18-I25+I27+I28+I29+I31 -> 218693 | ... M32: =M18-M25+M27+M28+M29+M31 -> 224897 | O32: 155000 | P32: =D32-O32 -> -239732.29

Sheet Assumptions
A1: Assumption | B1: Value | C1: Effective Date | D1: Notes
A2: FloorPlanRate | B2: 0.058 | C2: 2023-03-15 | D2: Annual floor plan interest rate — Source: Lender Agreement 2023
A3: TaxRate | B3: 0.21 | C3: 2023-01-01 | D3: Federal + state blended effective tax rate
A4: OverheadAllocationMethod | B4: revenue-weighted | C4: 2023-06-01 | D4: Method for allocating overhead across departments
A5: FI_PVR_Target | B5: 1600 | C5: 2024-08-20 | D5: Target F&I per vehicle retailed
A6: ServiceAbsorptionTarget | B6: 0.8 | C6: 2024-09-01 | D6: Target service absorption rate
A7: Toyota | B7: 0.021 | C7: 2024-11-01 | D7: Toyota OEM incentive allocation rate
A8: Honda | B8: 0.018 | C8: 2024-11-01 | D8: Honda OEM incentive allocation rate
A9: Ford | B9: 0.025 | C9: 2024-11-01 | D9: Ford OEM incentive allocation rate
A10: TotalOverhead_Mar | B10: 320000 | C10: 2024-12-01 | D10: Total dealership overhead for March — used in service absorption calc
A11: OwnerCompensationAddback | B11: 8000 | C11: 2024-11-15 | D11: Non-recurring owner compensation addback for EBITDA
A12: OneLegalCostAddback | B12: 5000 | C12: 2024-10-20 | D12: One-time legal cost addback for EBITDA
A15: DEPRECATED_OldFloorPlanRate | B15: 0.048 | C15: 2022-01-01 | D15: DEPRECATED — old floor plan rate, do not use
A16: DEPRECATED_OldTaxRate | B16: 0.25 | C16: 2021-06-15 | D16: DEPRECATED — pre-tax-reform rate, do not use

Sheet New Vehicle
A1: Deal# | B1: Stock# | C1: VIN | D1: Sale Date | E1: OEM | F1: Sale Price ($) | G1: Invoice Cost ($) | H1: Holdback ($) | I1: Incentive Alloc ($) | J1: Front Gross ($) | K1: F&I Rev ($) | L1: Month
A2: 1001 | B2: S2201 | C2: 1HGBH41JXMN001001 | D2: 2026-01-08 | E2: Toyota | F2: 29639 | G2: 27401 | H2: 548 | I2: =F2*VLOOKUP(E2,Assumptions!$A$7:$B$9,2,FALSE()) -> 622.419 | J2: =F2-G2+H2+I2 -> 3408.419 | K2: 1301 | L2: Jan
A3: 1002 | B3: S2202 | C3: 1HGBH41JXMN001002 | D3: 2026-01-18 | E3: Honda | F3: 34717 | G3: 31960 | H3: 639 | I3: =F3*VLOOKUP(E3,Assumptions!$A$7:$B$9,2,FALSE()) -> 624.906 | J3: =F3-G3+H3+I3 -> 4020.906 | K3: 2627 | L3: Jan
A4: 1003 | B4: S2203 | C4: 1HGBH41JXMN001003 | D4: 2026-01-07 | E4: Toyota | F4: 55651 | G4: 49079 | H4: 981 | I4: =F4*VLOOKUP(E4,Assumptions!$A$7:$B$9,2,FALSE()) -> 1168.671 | J4: =F4-G4+H4+I4 -> 8721.671 | K4: 991 | L4: Jan
A5: 1004 | B5: S2204 | C5: 1HGBH41JXMN001004 | D5: 2026-01-07 | E5: Honda | F5: 61118 | G5: 55991 | H5: 1119 | I5: =F5*VLOOKUP(E5,Assumptions!$A$7:$B$9,2,FALSE()) -> 1100.124 | J5: =F5-G5+H5+I5 -> 7346.124 | K5: 1949 | L5: Jan
A6: 1005 | B6: S2205 | C6: 1HGBH41JXMN001005 | D6: 2026-01-09 | E6: Honda | F6: 55493 | G6: 49567 | H6: 991 | I6: =F6*VLOOKUP(E6,Assumptions!$A$7:$B$9,2,FALSE()) -> 998.874 | J6: =F6-G6+H6+I6 -> 7915.874 | K6: 2006 | L6: Jan
A7: 1006 | B7: S2206 | C7: 1HGBH41JXMN001006 | D7: 2026-01-09 | E7: Toyota | F7: 38463 | G7: 35458 | H7: 709 | I7: =F7*VLOOKUP(E7,Assumptions!$A$7:$B$9,2,FALSE()) -> 807.723 | J7: =F7-G7+H7+I7 -> 4521.723 | K7: 1496 | L7: Jan
A8: 1007 | B8: S2207 | C8: 1HGBH41JXMN001007 | D8: 2026-01-04 | E8: Honda | F8: 42110 | G8: 39475 | H8: 789 | I8: =F8*VLOOKUP(E8,Assumptions!$A$7:$B$9,2,FALSE()) -> 757.98 | J8: =F8-G8+H8+I8 -> 4181.98 | K8: 1489 | L8: Jan
A9: 1008 | B9: S2208 | C9: 1HGBH41JXMN001008 | D9: 2026-01-12 | E9: Toyota | F9: 52898 | G9: 46857 | H9: 937 | I9: =F9*VLOOKUP(E9,Assumptions!$A$7:$B$9,2,FALSE()) -> 1110.858 | J9: =F9-G9+H9+I9 -> 8088.858 | K9: 2535 | L9: Jan
A10: 1009 | B10: S2209 | C10: 1HGBH41JXMN001009 | D10: 2026-01-15 | E10: Honda | F10: 45335 | G10: 42090 | H10: 841 | I10: =F10*VLOOKUP(E10,Assumptions!$A$7:$B$9,2,FALSE()) -> 816.03 | J10: =F10-G10+H10+I10 -> 4902.03 | K10: 2294 | L10: Jan
A11: 1010 | B11: S2210 | C11: 1HGBH41JXMN001010 | D11: 2026-01-03 | E11: Honda | F11: 36180 | G11: 33950 | H11: 679 | I11: =F11*VLOOKUP(E11,Assumptions!$A$7:$B$9,2,FALSE()) -> 651.24 | J11: =F11-G11+H11+I11 -> 3560.24 | K11: 1575 | L11: Jan
A12: 1011 | B12: S2211 | C12: 1HGBH41JXMN001011 | D12: 2026-01-28 | E12: Honda | F12: 47213 | G12: 43896 | H12: 877 | I12: =F12*VLOOKUP(E12,Assumptions!$A$7:$B$9,2,FALSE()) -> 849.834 | J12: =F12-G12+H12+I12 -> 5043.834 | K12: 2066 | L12: Jan
A13: 1012 | B13: S2212 | C13: 1HGBH41JXMN001012 | D13: 2026-01-22 | E13: Ford | F13: 40601 | G13: 37445 | H13: 748 | I13: =F13*VLOOKUP(E13,Assumptions!$A$7:$B$9,2,FALSE()) -> 1015.025 | J13: =F13-G13+H13+I13 -> 4919.025 | K13: 893 | L13: Jan
... A41: 1040 | B41: S2240 | C41: 1HGBH41JXMN001040 | D41: 2026-03-04 | E41: Ford | F41: 56711 | G41: 52966 | H41: 1059 | I41: =F41*VLOOKUP(E41,Assumptions!$A$7:$B$9,2,FALSE()) -> 1417.775 | J41: =F41-G41+H41+I41 -> 6221.775 | K41: 1724 | L41: Mar
A43: SUMMARY — MARCH
A44: Unit Count | B44: =COUNTIFS(L2:L41,"Mar") -> 14
A45: Total Front Gross ($) | B45: =SUMIFS(J2:J41,L2:L41,"Mar") -> 81057.72
A46: Avg Front Gross ($) | B46: =AVERAGEIFS(J2:J41,L2:L41,"Mar") -> 5789.8371
A47: Total F&I Revenue ($) | B47: =SUMIFS(K2:K41,L2:L41,"Mar") -> 24574
A48: Avg F&I PVR ($) | B48: =B47/B44 -> 1755.2857

Sheet Used Vehicle
A1: Deal# | B1: Stock# | C1: VIN | D1: Sale Date | E1: Days on Lot | F1: Acquisition Source | G1: Sale Price ($) | H1: Acq Cost ($) | I1: Recon Cost ($) | J1: Floor Plan Int ($) | K1: Adj Gross ($) | L1: Month
A2: 2001 | B2: U4001 | C2: 2T1BURHE0JC002001 | D2: 2026-01-19 | E2: 7 | F2: Direct | G2: 20123 | H2: 15076 | I2: 992 | J2: =E2*H2*FloorPlanRate/365 -> 16.769468 | K2: =G2-H2-I2-J2 -> 4038.2305 | L2: Jan
A3: 2002 | B3: U4002 | C3: 2T1BURHE0JC002002 | D3: 2026-01-23 | E3: 14 | F3: Direct | G3: 19540 | H3: 15563 | I3: 314 | J3: =E3*H3*FloorPlanRate/365 -> 34.622345 | K3: =G3-H3-I3-J3 -> 3628.3777 | L3: Jan
A4: 2003 | B4: U4003 | C4: 2T1BURHE0JC002003 | D4: 2026-01-28 | E4: 9 | F4: Auction | G4: 13929 | H4: 10443 | I4: 2154 | J4: =E4*H4*FloorPlanRate/365 -> 14.934921 | K4: =G4-H4-I4-J4 -> 1317.0651 | L4: Jan
A5: 2004 | B5: U4004 | C5: 2T1BURHE0JC002004 | D5: 2026-01-07 | E5: 67 | F5: Direct | G5: 14321 | H5: 11268 | I5: 870 | J5: =E5*H5*FloorPlanRate/365 -> 119.96561 | K5: =G5-H5-I5-J5 -> 2063.0344 | L5: Jan
A6: 2005 | B6: U4005 | C6: 2T1BURHE0JC002005 | D6: 2026-01-08 | E6: 65 | F6: Auction | G6: 16335 | H6: 13297 | I6: 2107 | J6: =E6*H6*FloorPlanRate/365 -> 137.34162 | K6: =G6-H6-I6-J6 -> 793.65838 | L6: Jan
A7: 2006 | B7: U4006 | C7: 2T1BURHE0JC002006 | D7: 2026-01-12 | E7: 60 | F7: Auction | G7: 25338 | H7: 18870 | I7: 498 | J7: =E7*H7*FloorPlanRate/365 -> 179.91123 | K7: =G7-H7-I7-J7 -> 5790.0888 | L7: Jan
A8: 2007 | B8: U4007 | C8: 2T1BURHE0JC002007 | D8: 2026-01-22 | E8: 11 | F8: Direct | G8: 25470 | H8: 19884 | I8: 1793 | J8: =E8*H8*FloorPlanRate/365 -> 34.756142 | K8: =G8-H8-I8-J8 -> 3758.2439 | L8: Jan
A9: 2008 | B9: U4008 | C9: 2T1BURHE0JC002008 | D9: 2026-01-26 | E9: 48 | F9: Trade-in | G9: 33174 | H9: 24309 | I9: 1124 | J9: =E9*H9*FloorPlanRate/365 -> 185.4144 | K9: =G9-H9-I9-J9 -> 7555.5856 | L9: Jan
A10: 2009 | B10: U4009 | C10: 2T1BURHE0JC002009 | D10: 2026-01-05 | E10: 62 | F10: Auction | G10: 20147 | H10: 15007 | I10: 1398 | J10: =E10*H10*FloorPlanRate/365 -> 147.84979 | K10: =G10-H10-I10-J10 -> 3594.1502 | L10: Jan
A11: 2010 | B11: U4010 | C11: 2T1BURHE0JC002010 | D11: 2026-01-15 | E11: 14 | F11: Direct | G11: 18012 | H11: 13620 | I11: 811 | J11: =E11*H11*FloorPlanRate/365 -> 30.299836 | K11: =G11-H11-I11-J11 -> 3550.7002 | L11: Jan
A12: 2011 | B12: U4011 | C12: 2T1BURHE0JC002011 | D12: 2026-02-03 | E12: 6 | F12: Trade-in | G12: 15208 | H12: 11049 | I12: 1407 | J12: =E12*H12*FloorPlanRate/365 -> 10.534389 | K12: =G12-H12-I12-J12 -> 2741.4656 | L12: Feb
A13: 2012 | B13: U4012 | C13: 2T1BURHE0JC002012 | D13: 2026-02-28 | E13: 32 | F13: Auction | G13: 17449 | H13: 13485 | I13: 1285 | J13: =E13*H13*FloorPlanRate/365 -> 68.570301 | K13: =G13-H13-I13-J13 -> 2610.4297 | L13: Feb
... A22: 2021 | B22: U4021 | C22: 2T1BURHE0JC002021 | D22: 2026-03-09 | E22: 35 | F22: Auction | G22: 18693 | H22: 15086 | I22: 943 | J22: =E22*H22*FloorPlanRate/365 -> 83.902959 | K22: =G22-H22-I22-J22 -> 2580.097 | L22: Mar
A23: 2022 | B23: U4022 | C23: 2T1BURHE0JC002022 | D23: 2026-03-11 | E23: 63 | F23: Trade-in | G23: 16288 | H23: 13149 | I23: 914 | J23: =E23*H23*FloorPlanRate/365 -> 131.6341 | K23: 3200 | L23: Mar
A24: 2023 | B24: U4023 | C24: 2T1BURHE0JC002023 | D24: 2026-03-03 | E24: 17 | F24: Direct | G24: 12305 | H24: 9592 | I24: 1453 | J24: =E24*H24*FloorPlanRate/365 -> 25.91154 | K24: =G24-H24-I24-J24 -> 1234.0885 | L24: Mar
A25: 2024 | B25: U4024 | C25: 2T1BURHE0JC002024 | D25: 2026-03-03 | E25: 49 | F25: Trade-in | G25: 18984 | H25: 14916 | I25: 571 | J25: =E25*H25*FloorPlanRate/365 -> 116.14047 | K25: =G25-H25-I25-J25 -> 3380.8595 | L25: Mar
A26: 2025 | B26: U4025 | C26: 2T1BURHE0JC002025 | D26: 2026-03-23 | E26: 74 | F26: Auction | G26: 24108 | H26: 18250 | I26: 1197 | J26: =E26*H26*FloorPlanRate/365 -> 214.6 | K26: =G26-H26-I26-J26 -> 4446.4 | L26: Mar
A27: 2026 | B27: U4026 | C27: 2T1BURHE0JC002026 | D27: 2026-03-01 | E27: 72 | F27: Direct | G27: 32043 | H27: 27169 | I27: 1952 | J27: =E27*H27*FloorPlanRate/365 -> 310.84313 | K27: =G27-H27-I27-J27 -> 2611.1569 | L27: Mar
A28: 2027 | B28: U4027 | C28: 2T1BURHE0JC002027 | D28: 2026-03-05 | E28: 18 | F28: Auction | G28: 30173 | H28: 22898 | I28: 1658 | J28: =E28*H28*FloorPlanRate/365 -> 65.494553 | K28: =G28-H28-I28-J28 -> 5551.5054 | L28: Mar
A29: 2028 | B29: U4028 | C29: 2T1BURHE0JC002028 | D29: 2026-03-05 | E29: 75 | F29: Auction | G29: 15782 | H29: 13188 | I29: 1820 | J29: =E29*H29*FloorPlanRate/365 -> 157.17205 | K29: =G29-H29-I29-J29 -> 616.82795 | L29: Mar
A30: 2029 | B30: U4029 | C30: 2T1BURHE0JC002029 | D30: 2026-03-07 | E30: 48 | F30: Direct | G30: 21232 | H30: 16956 | I30: 1769 | J30: =E30*H30*FloorPlanRate/365 -> 129.33015 | K30: =G30-H30-I30-J30 -> 2377.6699 | L30: Mar
A31: 2030 | B31: U4030 | C31: 2T1BURHE0JC002030 | D31: 2026-03-09 | E31: 67 | F31: Trade-in | G31: 32782 | H31: 27237 | I31: 1335 | J31: =E31*H31*FloorPlanRate/365 -> 289.98077 | K31: =G31-H31-I31-J31 -> 3920.0192 | L31: Mar
A32: 2031 | B32: U4031 | C32: 2T1BURHE0JC002031 | D32: 2026-03-02 | E32: 40 | F32: Trade-in | G32: 15024 | H32: 12056 | I32: 1998 | J32: =E32*H32*FloorPlanRate/365 -> 76.629918 | K32: =G32-H32-I32-J32 -> 893.37008 | L32: Mar
A34: SUMMARY — MARCH
A35: Unit Count | B35: =COUNTIFS(L2:L32,"Mar") -> 11
A36: Total Adj Gross ($) | B36: =SUMIFS(K2:K32,L2:L32,"Mar") -> 30811.994
A37: Avg Adj Gross ($) | B37: =AVERAGEIFS(K2:K32,L2:L32,"Mar") -> 2801.0904
A38: Wtd Avg Recon Cost ($) | B38: =SUMPRODUCT((L2:L32="Mar")*(I2:I32)*(E2:E32))/SUMIFS(E2:E32,L2:L32,"Mar") -> 1421.1649

Sheet F&I Detail
A1: Deal# | B1: Deal Type | C1: Product Type | D1: Product Cost ($) | E1: Product Revenue ($) | F1: Reserve ($) | G1: Penetration | H1: Month
A2: 1001 | B2: New | C2: GAP | D2: 852 | E2: 1320 | F2: 163 | G2: Yes | H2: Jan
A3: 1001 | B3: New | C3: Tire & Wheel | D3: 774 | E3: 983 | F3: 114 | G3: Yes | H3: Jan
A4: 1002 | B4: New | C4: GAP | D4: 758 | E4: 994 | F4: 223 | G4: Yes | H4: Jan
A5: 1002 | B5: New | C5: GAP | D5: 640 | E5: 970 | F5: 103 | G5: Yes | H5: Jan
A6: 1002 | B6: New | C6: VSC | D6: 566 | E6: 981 | F6: 198 | G6: Yes | H6: Jan
A7: 1003 | B7: New | C7: Life/A&H | D7: 616 | E7: 1813 | F7: 350 | G7: No | H7: Jan
A8: 1003 | B8: New | C8: GAP | D8: 366 | E8: 1565 | F8: 344 | G8: No | H8: Jan
A9: 1004 | B9: New | C9: VSC | D9: 383 | E9: 1337 | F9: 319 | G9: Yes | H9: Jan
A10: 1004 | B10: New | C10: Tire & Wheel | D10: 885 | E10: 1969 | F10: 413 | G10: No | H10: Jan
A11: 1005 | B11: New | C11: VSC | D11: 591 | E11: 1684 | F11: 178 | G11: Yes | H11: Jan
A12: 1006 | B12: New | C12: Tire & Wheel | D12: 558 | E12: 1070 | F12: 238 | G12: Yes | H12: Jan
A13: 1007 | B13: New | C13: VSC | D13: 875 | E13: 1272 | F13: 203 | G13: Yes | H13: Jan
... A83: 1040 | B83: New | C83: VSC | D83: 787 | E83: 1278 | F83: 217 | G83: Yes | H83: Mar
A85: F&I SUMMARY — MARCH
A86: Total F&I Revenue ($) | B86: =SUMIFS(E2:E83,H2:H83,"Mar") -> 40457
A87: Deal Count | B87: ='New Vehicle'!$B$44 -> 14
A88: F&I PVR ($) | B88: =B86/B87 -> 2889.7857
A89: PVR Target ($) | B89: =FI_PVR_Target -> 1600
A90: PVR vs Target ($) | B90: =B88-B89 -> 1289.7857

Sheet Service & Parts
A1: RO# | B1: Date | C1: Type | D1: Labor Rev ($) | E1: Parts Rev ($) | F1: Labor Cost ($) | G1: Parts Cost ($) | H1: Month
A2: 5001 | B2: 2026-01-27 | C2: Customer Pay | D2: 255 | E2: 308 | F2: 162 | G2: 198 | H2: Jan
A3: 5002 | B3: 2026-01-02 | C3: Customer Pay | D3: 970 | E3: 553 | F3: 450 | G3: 373 | H3: Jan
A4: 5003 | B4: 2026-01-08 | C4: Customer Pay | D4: 455 | E4: 880 | F4: 255 | G4: 537 | H4: Jan
A5: 5004 | B5: 2026-01-20 | C5: Customer Pay | D5: 1292 | E5: 832 | F5: 688 | G5: 556 | H5: Jan
A6: 5005 | B6: 2026-01-10 | C6: Customer Pay | D6: 1738 | E6: 585 | F6: 914 | G6: 428 | H6: Jan
A7: 5006 | B7: 2026-01-24 | C7: Internal | D7: 1028 | E7: 362 | F7: 579 | G7: 203 | H7: Jan
A8: 5007 | B8: 2026-01-03 | C8: Customer Pay | D8: 1712 | E8: 262 | F8: 984 | G8: 157 | H8: Jan
A9: 5008 | B9: 2026-01-14 | C9: Customer Pay | D9: 641 | E9: 227 | F9: 359 | G9: 131 | H9: Jan
A10: 5009 | B10: 2026-01-10 | C10: Warranty | D10: 1561 | E10: 658 | F10: 849 | G10: 366 | H10: Jan
A11: 5010 | B11: 2026-01-08 | C11: Internal | D11: 729 | E11: 769 | F11: 453 | G11: 433 | H11: Jan
A12: 5011 | B12: 2026-01-07 | C12: Warranty | D12: 1763 | E12: 860 | F12: 1013 | G12: 586 | H12: Jan
A13: 5012 | B13: 2026-01-09 | C13: Warranty | D13: 385 | E13: 607 | F13: 190 | G13: 351 | H13: Jan
... A166: 5165 | B166: 2026-03-10 | C166: Internal | D166: 1481 | E166: 393 | F166: 900 | G166: 226 | H166: Mar
A168: SERVICE & PARTS SUMMARY — MARCH
A169: Total Labor Revenue ($) | B169: =SUMIFS(D2:D166,H2:H166,"Mar") -> 51166
A170: Total Parts Revenue ($) | B170: =SUMIFS(E2:E166,H2:H166,"Mar") -> 25066
A171: Total Labor Cost ($) | B171: =SUMIFS(F2:F166,H2:H166,"Mar") -> 28096
A172: Total Parts Cost ($) | B172: =SUMIFS(G2:G166,H2:H166,"Mar") -> 16494
A173: Service Gross ($) | B173: =B169-B171 -> 23070
A174: Parts Gross ($) | B174: =B170-B172 -> 8572
A175: Total S&P Gross ($) | B175: =B173+B174 -> 31642
A176: Service Absorption Rate | B176: =(B173+B174)/Assumptions!$B$10 -> 0.09888125
