Workbook
Name AnnualDegradationRate: Assumptions!$B$2
Name DiscountRate: Assumptions!$B$3
Name ITCRate: Assumptions!$B$4
Name OM_EscalationRate: Assumptions!$B$5
Name LandLeaseEscalation: Assumptions!$B$6
Name InsuranceEscalation: Assumptions!$B$7
Name TaxEquitySplit: Assumptions!$B$8
Name TaxEquityFlipDate: Assumptions!$B$10
Name DefaultPriceCurveSheet: Assumptions!$B$11
Name Alpha_DegradationOverride: Assumptions!$B$15
Name Gamma_EscalationCap: Assumptions!$B$16

Sheet Portfolio Summary
A1: Site | B1: Capacity (MW) | C1: Expected Yield (MWh) | D1: Contract Type | E1: Contract Rate | F1: Expected Revenue | G1: System Loss | H1: Performance Ratio | I1: Net Operating Income
A2: Alpha | B2: 13.2 | C2: 22560 | D2: PPA | E2: 68.99 | F2: =IF(D2="PPA",C2*E2,IF(D2="Merchant",C2*VLOOKUP("Jan",'Price Curves'!A:B,2,FALSE),C2*MAX(VLOOKUP("Jan",'Price Curves'!A:B,2,FALSE),VLOOKUP("Jan",'Price Curves'!A:C,3,FALSE)))) | G2: =VLOOKUP(A2,'System Losses'!A:H,8,FALSE) | H2: =(1-G2)*VLOOKUP(A2,Weather!A:Z,26,FALSE) | I2: =F2-VLOOKUP(A2,'O&M Costs'!A:G,7,FALSE)
A3: Beta | B3: 28.3 | C3: 50708 | D3: Merchant | E3: 59.31 | F3: =IF(D3="PPA",C3*E3,IF(D3="Merchant",C3*VLOOKUP("Jan",'Price Curves'!A:B,2,FALSE),C3*MAX(VLOOKUP("Jan",'Price Curves'!A:B,2,FALSE),VLOOKUP("Jan",'Price Curves'!A:C,3,FALSE)))) | G3: =VLOOKUP(A3,'System Losses'!A:H,8,FALSE) | H3: =(1-G3)*VLOOKUP(A3,Weather!A:Z,26,FALSE) | I3: =F3-VLOOKUP(A3,'O&M Costs'!A:G,7,FALSE)
A4: Gamma | B4: 16.1 | C4: 31595 | D4: Hybrid | E4: 86.41 | F4: =IF(D4="PPA",C4*E4,IF(D4="Merchant",C4*VLOOKUP("Jan",'Price Curves'!A:B,2,FALSE),C4*MAX(VLOOKUP("Jan",'Price Curves'!A:B,2,FALSE),VLOOKUP("Jan",'Price Curves'!A:C,3,FALSE)))) | G4: =VLOOKUP(A4,'System Losses'!A:H,8,FALSE) | H4: =(1-G4)*VLOOKUP(A4,Weather!A:Z,26,FALSE) | I4: =F4-VLOOKUP(A4,'O&M Costs'!A:G,7,FALSE)
A5: Delta | B5: 6.8 | C5: 12792 | D5: PPA | E5: 81.51 | F5: =IF(D5="PPA",C5*E5,IF(D5="Merchant",C5*VLOOKUP("Jan",'Price Curves'!A:B,2,FALSE),C5*MAX(VLOOKUP("Jan",'Price Curves'!A:B,2,FALSE),VLOOKUP("Jan",'Price Curves'!A:C,3,FALSE)))) | G5: =VLOOKUP(A5,'System Losses'!A:H,8,FALSE) | H5: =(1-G5)*VLOOKUP(A5,Weather!A:Z,26,FALSE) | I5: =F5-VLOOKUP(A5,'O&M Costs'!A:G,7,FALSE)
A6: Epsilon | B6: 6.7 | C6: 13528 | D6: PPA | E6: 59.12 | F6: =IF(D6="PPA",C6*E6,IF(D6="Merchant",C6*VLOOKUP("Jan",'Price Curves'!A:B,2,FALSE),C6*MAX(VLOOKUP("Jan",'Price Curves'!A:B,2,FALSE),VLOOKUP("Jan",'Price Curves'!A:C,3,FALSE)))) | G6: =VLOOKUP(A6,'System Losses'!A:H,8,FALSE) | H6: =(1-G6)*VLOOKUP(A6,Weather!A:Z,26,FALSE) | I6: =F6-VLOOKUP(A6,'O&M Costs'!A:G,7,FALSE)
A7: Zeta | B7: 32 | C7: 60001 | D7: Merchant | E7: 76.95 | F7: =IF(D7="PPA",C7*E7,IF(D7="Merchant",C7*VLOOKUP("Jan",'Price Curves'!A:B,2,FALSE),C7*MAX(VLOOKUP("Jan",'Price Curves'!A:B,2,FALSE),VLOOKUP("Jan",'Price Curves'!A:C,3,FALSE)))) | G7: =VLOOKUP(A7,'System Losses'!A:H,8,FALSE) | H7: =(1-G7)*VLOOKUP(A7,Weather!A:Z,26,FALSE) | I7: =F7-VLOOKUP(A7,'O&M Costs'!A:G,7,FALSE)
A8: Eta | B8: 18.8 | C8: 34029 | D8: Hybrid | E8: 75.39 | F8: =IF(D8="PPA",C8*E8,IF(D8="Merchant",C8*VLOOKUP("Jan",'Price Curves'!A:B,2,FALSE),C8*MAX(VLOOKUP("Jan",'Price Curves'!A:B,2,FALSE),VLOOKUP("Jan",'Price Curves'!A:C,3,FALSE)))) | G8: =VLOOKUP(A8,'System Losses'!A:H,8,FALSE) | H8: =(1-G8)*VLOOKUP(A8,Weather!A:Z,26,FALSE) | I8: =F8-VLOOKUP(A8,'O&M Costs'!A:G,7,FALSE)
A9: Theta | B9: 24.2 | C9: 46692 | D9: PPA | E9: 70.64 | F9: =IF(D9="PPA",C9*E9,IF(D9="Merchant",C9*VLOOKUP("Jan",'Price Curves'!A:B,2,FALSE),C9*MAX(VLOOKUP("Jan",'Price Curves'!A:B,2,FALSE),VLOOKUP("Jan",'Price Curves'!A:C,3,FALSE)))) | G9: =VLOOKUP(A9,'System Losses'!A:H,8,FALSE) | H9: =(1-G9)*VLOOKUP(A9,Weather!A:Z,26,FALSE) | I9: =F9-VLOOKUP(A9,'O&M Costs'!A:G,7,FALSE)
A10: Iota | B10: 24.7 | C10: 39809 | D10: Merchant | E10: 76.66 | F10: =IF(D10="PPA",C10*E10,IF(D10="Merchant",C10*VLOOKUP("Jan",'Price Curves'!A:B,2,FALSE),C10*MAX(VLOOKUP("Jan",'Price Curves'!A:B,2,FALSE),VLOOKUP("Jan",'Price Curves'!A:C,3,FALSE)))) | G10: =VLOOKUP(A10,'System Losses'!A:H,8,FALSE) | H10: =(1-G10)*VLOOKUP(A10,Weather!A:Z,26,FALSE) | I10: =F10-VLOOKUP(A10,'O&M Costs'!A:G,7,FALSE)
A11: Kappa | B11: 27 | C11: 46376 | D11: PPA | E11: 81.72 | F11: =IF(D11="PPA",C11*E11,IF(D11="Merchant",C11*VLOOKUP("Jan",'Price Curves'!A:B,2,FALSE),C11*MAX(VLOOKUP("Jan",'Price Curves'!A:B,2,FALSE),VLOOKUP("Jan",'Price Curves'!A:C,3,FALSE)))) | G11: =VLOOKUP(A11,'System Losses'!A:H,8,FALSE) | H11: =(1-G11)*VLOOKUP(A11,Weather!A:Z,26,FALSE) | I11: =F11-VLOOKUP(A11,'O&M Costs'!A:G,7,FALSE)
A13: PORTFOLIO TOTAL | B13: =SUM(B2:B11) | C13: =SUM(C2:C11) | F13: =SUM(F2:F11) | I13: =SUM(I2:I11)
A14: Weighted Avg PR | H14: =SUMPRODUCT(B2:B11,H2:H11)/SUM(B2:B11)

Sheet Assumptions
A1: Assumption | B1: Value | C1: Effective Date | D1: Notes
A2: AnnualDegradationRate | B2: 0.005 | C2: 45658 | D2: Default annual panel degradation
A3: DiscountRate | B3: 0.08 | C3: 44986 | D3: STALE — project WACC
A4: ITCRate | B4: 0.3 | C4: 45444 | D4: Investment tax credit rate
A5: OM_EscalationRate | B5: 0.025 | C5: 45658 | D5: O&M cost escalation
A6: LandLeaseEscalation | B6: 0.02 | C6: 45658 | D6: Land lease escalation
A7: InsuranceEscalation | B7: 0.03 | C7: 44927 | D7: STALE — insurance escalation
A8: TaxEquitySplit | B8: 0.995 | C8: 45444 | D8: Pre-flip tax equity split
A9: PostFlipSplit | B9: 0.05 | C9: 45444 | D9: Post-flip tax equity split
A10: TaxEquityFlipDate | B10: 46905 | C10: 45444 | D10: Flip date
A11: DefaultPriceCurveSheet | B11: Price Curves | C11: 45658 | D11: Sheet used by INDIRECT
A12: PortfolioWideDegradation | B12: 0.005 | C12: 45658 | D12: Also default
A15: Alpha_DegradationOverride | B15: 0.007 | C15: 45689 | D15: Site Alpha override
A16: Gamma_EscalationCap | B16: 0.02 | C16: 45689 | D16: Site Gamma escalation cap

Sheet Generation
A1: Site | B1: Inverter | C1: Month | D1: kWh Generated | E1: Availability | F1: Curtailment kWh | G1: Net Generation
A2: Alpha | B2: INV-AL-1 | C2: Jan | D2: 134890 | E2: 0.9927 | F2: 1617 | G2: =D2-F2
A3: Alpha | B3: INV-AL-1 | C3: Feb | D3: 62657 | E3: 0.9533 | F3: 2194 | G3: =D3-F3
A4: Alpha | B4: INV-AL-1 | C4: Mar | D4: 74675 | E4: 0.9665 | F4: 237 | G4: =D4-F4
A5: Alpha | B5: INV-AL-1 | C5: Apr | D5: 183021 | E5: 0.9597 | F5: 352 | G5: =D5-F5
A6: Alpha | B6: INV-AL-1 | C6: May | D6: 163677 | E6: 0.9688 | F6: 985 | G6: =D6-F6
A7: Alpha | B7: INV-AL-1 | C7: Jun | D7: 73779 | E7: 0.9748 | F7: 242 | G7: =D7-F7
A8: Alpha | B8: INV-AL-1 | C8: Jul | D8: 198230 | E8: 0.9556 | F8: 914 | G8: =D8-F8
A9: Alpha | B9: INV-AL-1 | C9: Aug | D9: 66216 | E9: 0.976 | F9: 1624 | G9: =D9-F9
A10: Alpha | B10: INV-AL-1 | C10: Sep | D10: 62999 | E10: 0.9939 | F10: 190 | G10: =D10-F10
A11: Alpha | B11: INV-AL-1 | C11: Oct | D11: 195926 | E11: 0.9886 | F11: 1186 | G11: =D11-F11
A12: Alpha | B12: INV-AL-1 | C12: Nov | D12: 159874 | E12: 0.9565 | F12: 482 | G12: =D12-F12
A13: Alpha | B13: INV-AL-1 | C13: Dec | D13: 199661 | E13: 0.9639 | F13: 2793 | G13: =D13-F13
... A241: Kappa | B241: INV-KA-2 | C241: Dec | D241: 153381 | E241: 0.9554 | F241: 2634 | G241: =D241-F241
A242: TOTAL BY SITE
A243: Alpha | D243: =SUMIFS(G2:G241,A2:A241,"Alpha")
A244: Beta | D244: =SUMIFS(G2:G241,A2:A241,"Beta")
A245: Gamma | D245: =SUMIFS(G2:G241,A2:A241,"Gamma")
A246: Delta | D246: =SUMIFS(G2:G241,A2:A241,"Delta")
A247: Epsilon | D247: =SUMIFS(G2:G241,A2:A241,"Epsilon")
A248: Zeta | D248: =SUMIFS(G2:G241,A2:A241,"Zeta")
A249: Eta | D249: =SUMIFS(G2:G241,A2:A241,"Eta")
A250: Theta | D250: =SUMIFS(G2:G241,A2:A241,"Theta")
A251: Iota | D251: =SUMIFS(G2:G241,A2:A241,"Iota")
A252: Kappa | D252: =SUMIFS(G2:G241,A2:A241,"Kappa")

Sheet System Losses
A1: Site | B1: Soiling | C1: Shading | D1: Wiring | E1: Transformer | F1: Availability | G1: Degradation | H1: Total Loss
A2: Alpha | B2: 0.0132 | C2: 0.0081 | D2: 0.0141 | E2: 0.015 | F2: 0.0083 | G2: =Alpha_DegradationOverride | H2: =1-PRODUCT(1-B2,1-C2,1-D2,1-E2,1-F2,1-G2)
A3: Beta | B3: 0.0281 | C3: 0.0199 | D3: 0.0095 | E3: 0.0114 | F3: 0.0079 | G3: =AnnualDegradationRate | H3: =1-PRODUCT(1-B3,1-C3,1-D3,1-E3,1-F3,1-G3)
A4: Gamma | B4: 0.0118 | C4: 0.0101 | D4: 0.0059 | E4: 0.0124 | F4: 0.0089 | G4: =AnnualDegradationRate | H4: =1-PRODUCT(1-B4,1-C4,1-D4,1-E4,1-F4,1-G4)
A5: Delta | B5: 0.0214 | C5: 0.0183 | D5: 0.0125 | E5: 0.0141 | F5: 0.0112 | G5: =AnnualDegradationRate | H5: =1-PRODUCT(1-B5,1-C5,1-D5,1-E5,1-F5,1-G5)
A6: Epsilon | B6: 0.0205 | C6: 0.0107 | D6: 0.0084 | E6: 0.0106 | F6: 0.0092 | G6: =AnnualDegradationRate | H6: =1-PRODUCT(1-B6,1-C6,1-D6,1-E6,1-F6,1-G6)
A7: Zeta | B7: 0.0294 | C7: 0.0069 | D7: 0.01 | E7: 0.0163 | F7: 0.0179 | G7: =AnnualDegradationRate | H7: =1-PRODUCT(1-B7,1-C7,1-D7,1-E7,1-F7,1-G7)
A8: Eta | B8: 0.0143 | C8: 0.0091 | D8: 0.0075 | E8: 0.014 | F8: 0.0117 | G8: =AnnualDegradationRate | H8: =1-PRODUCT(1-B8,1-C8,1-D8,1-E8,1-F8,1-G8)
A9: Theta | B9: 0.0291 | C9: 0.0177 | D9: 0.0137 | E9: 0.0102 | F9: 0.0055 | G9: =AnnualDegradationRate | H9: =1-PRODUCT(1-B9,1-C9,1-D9,1-E9,1-F9,1-G9)
A10: Iota | B10: 0.0242 | C10: 0.0184 | D10: 0.0097 | E10: 0.0159 | F10: 0.005 | G10: =AnnualDegradationRate | H10: =1-PRODUCT(1-B10,1-C10,1-D10,1-E10,1-F10,1-G10)
A11: Kappa | B11: 0.0178 | C11: 0.0189 | D11: 0.0133 | E11: 0.0186 | F11: 0.0196 | G11: =AnnualDegradationRate | H11: =1-PRODUCT(1-B11,1-C11,1-D11,1-E11,1-F11,1-G11)

Sheet Weather
A1: Site | B1: TMY_Jan | C1: TMY_Feb | D1: TMY_Mar | E1: TMY_Apr | F1: TMY_May | G1: TMY_Jun | H1: TMY_Jul | I1: TMY_Aug | J1: TMY_Sep | K1: TMY_Oct | L1: TMY_Nov | M1: TMY_Dec | N1: Actual_Jan | O1: Actual_Feb | P1: Actual_Mar | Q1: Actual_Apr | R1: Actual_May | S1: Actual_Jun | T1: Actual_Jul | U1: Actual_Aug | V1: Actual_Sep | W1: Actual_Oct | X1: Actual_Nov | Y1: Actual_Dec | Z1: WeatherAdj
A2: Alpha | B2: 139.9 | C2: 132.4 | D2: 174.6 | E2: 177.7 | F2: 181.2 | G2: 164.1 | H2: 182.6 | I2: 193.6 | J2: 144.3 | K2: 140.1 | L2: 175.9 | M2: 125.6 | N2: 120.9 | O2: 162.2 | P2: 204.1 | Q2: 174.7 | R2: 155.7 | S2: 114 | T2: 133.3 | U2: 174.6 | V2: 122.8 | W2: 173.6 | X2: 121.2 | Y2: 162.4 | Z2: =SUM(N2:Y2)/SUM(B2:M2)
A3: Beta | B3: 166.6 | C3: 137.9 | D3: 120.8 | E3: 156.9 | F3: 171.6 | G3: 158 | H3: 139.8 | I3: 176.4 | J3: 121.7 | K3: 174 | L3: 140.6 | M3: 194 | N3: 148.8 | O3: 170.1 | P3: 140.2 | Q3: 205.9 | R3: 198.4 | S3: 133.5 | T3: 206.1 | U3: 140.7 | V3: 159.8 | W3: 152 | X3: 176.7 | Y3: 132.7 | Z3: =SUM(N3:Y3)/SUM(B3:M3)
A4: Gamma | B4: 122.7 | C4: 153.6 | D4: 135.8 | E4: 179.1 | F4: 136.4 | G4: 144.9 | H4: 138.5 | I4: 180.8 | J4: 196.2 | K4: 135 | L4: 153.4 | M4: 195.9 | N4: 143.8 | O4: 178.3 | P4: 189.7 | Q4: 160.5 | R4: 207 | S4: 192 | T4: 132.1 | U4: 139.5 | V4: 159.6 | W4: 132.3 | X4: 176.5 | Y4: 124.6 | Z4: =SUM(N4:Y4)/SUM(B4:M4)
A5: Delta | B5: 151.5 | C5: 197.9 | D5: 124.1 | E5: 151.5 | F5: 190.7 | G5: 199.8 | H5: 146.3 | I5: 194.9 | J5: 122.6 | K5: 150.3 | L5: 146.5 | M5: 120.2 | N5: 131.3 | O5: 124.2 | P5: 116 | Q5: 199.8 | R5: 183.3 | S5: 203.2 | T5: 128.6 | U5: 184.6 | V5: 176.4 | W5: 147.4 | X5: 126.9 | Y5: 138 | Z5: =SUM(N5:Y5)/SUM(B5:M5)
A6: Epsilon | B6: 148.1 | C6: 129.9 | D6: 136.6 | E6: 185.7 | F6: 154.6 | G6: 157.9 | H6: 193.6 | I6: 149.1 | J6: 122.4 | K6: 184.9 | L6: 123.3 | M6: 125 | N6: 205.6 | O6: 206.4 | P6: 145.7 | Q6: 192.2 | R6: 114.9 | S6: 147.3 | T6: 129.3 | U6: 199.7 | V6: 151.1 | W6: 186.7 | X6: 113.5 | Y6: 202 | Z6: =SUM(N6:Y6)/SUM(B6:M6)
A7: Zeta | B7: 140.6 | C7: 191.9 | D7: 141.8 | E7: 169.4 | F7: 177.3 | G7: 142.1 | H7: 180.5 | I7: 170.7 | J7: 121.9 | K7: 158 | L7: 196.3 | M7: 140.1 | N7: 184.7 | O7: 143.9 | P7: 205.8 | Q7: 136.2 | R7: 141.6 | S7: 110.4 | T7: 201.6 | U7: 204.3 | V7: 133.4 | W7: 205.7 | X7: 148.7 | Y7: 153 | Z7: =SUM(N7:Y7)/SUM(B7:M7)
A8: Eta | B8: 159.5 | C8: 134.6 | D8: 179.1 | E8: 181.8 | F8: 146.2 | G8: 148.9 | H8: 126.3 | I8: 180.2 | J8: 125.2 | K8: 164.2 | L8: 198.4 | M8: 199 | N8: 202.8 | O8: 190.3 | P8: 192.3 | Q8: 170.7 | R8: 142 | S8: 188.2 | T8: 129.7 | U8: 134.7 | V8: 113.4 | W8: 142.6 | X8: 198.3 | Y8: 136.5 | Z8: =SUM(N8:Y8)/SUM(B8:M8)
A9: Theta | B9: 126.7 | C9: 159.9 | D9: 155.8 | E9: 153.3 | F9: 173.9 | G9: 187.8 | H9: 129.7 | I9: 143.5 | J9: 149.8 | K9: 135.9 | L9: 139.6 | M9: 190.7 | N9: 119.6 | O9: 181 | P9: 133.4 | Q9: 172 | R9: 184.8 | S9: 176.4 | T9: 194.1 | U9: 166.7 | V9: 183.8 | W9: 134.7 | X9: 125.3 | Y9: 167.8 | Z9: =SUM(N9:Y9)/SUM(B9:M9)
A10: Iota | B10: 146.1 | C10: 199.4 | D10: 138.5 | E10: 172.3 | F10: 128.2 | G10: 185.5 | H10: 193.2 | I10: 143.5 | J10: 135.2 | K10: 166.7 | L10: 149.8 | M10: 155.9 | N10: 149.6 | O10: 160.7 | P10: 190.8 | Q10: 209.1 | R10: 157.5 | S10: 194.1 | T10: 114 | U10: 121.9 | V10: 207.3 | W10: 203 | X10: 196.6 | Y10: 136 | Z10: =SUM(N10:Y10)/SUM(B10:M10)
A11: Kappa | B11: 182.2 | C11: 128.5 | D11: 169.6 | E11: 149.5 | F11: 136.3 | G11: 168 | H11: 136.3 | I11: 146.2 | J11: 134.8 | K11: 136.3 | L11: 163.8 | M11: 128.1 | N11: 204.6 | O11: 169.6 | P11: 131.8 | Q11: 124.1 | R11: 135.5 | S11: 175.2 | T11: 111.1 | U11: 177.8 | V11: 141.2 | W11: 189.5 | X11: 116.3 | Y11: 149.5 | Z11: =SUM(N11:Y11)/SUM(B11:M11)

Sheet Price Curves
A1: Month | B1: Merchant Price | C1: Hybrid Floor
A2: Jan | B2: 67.01 | C2: 47.78
A3: Feb | B3: 48.65 | C3: 38.27
A4: Mar | B4: 72.82 | C4: 43.2
A5: Apr | B5: 56.33 | C5: 41.15
A6: May | B6: 83.13 | C6: 41.25
A7: Jun | B7: 67.66 | C7: 42.14
A8: Jul | B8: 61.66 | C8: 52.28
A9: Aug | B9: 84.86 | C9: 42.28
A10: Sep | B10: 52.89 | C10: 49.56
A11: Oct | B11: 53.15 | C11: 35.12
A12: Nov | B12: 81.07 | C12: 43.48
A13: Dec | B13: 77.81 | C13: 43.12
A20: Dynamic Jan Merchant (via INDIRECT) | B20: =INDIRECT(DefaultPriceCurveSheet&"!B2")

Sheet O&M Costs
A1: Site | B1: O&M Annual | C1: Insurance | D1: Land Lease | E1: Property Tax | F1: Asset Mgmt Fee | G1: Total Opex
A2: Alpha | B2: 175611 | C2: 25102 | D2: 30652 | E2: 19259 | F2: 8243 | G2: =SUM(B2:F2)
A3: Beta | B3: 93551 | C3: 28073 | D3: 29338 | E3: 35993 | F3: 14499 | G3: =SUM(B3:F3)
A4: Gamma | B4: 103338 | C4: 28771 | D4: 44303 | E4: 39158 | F4: 16265 | G4: =SUM(B4:F4)
A5: Delta | B5: 125006 | C5: 14780 | D5: 42802 | E5: 24283 | F5: 10651 | G5: =SUM(B5:F5)
A6: Epsilon | B6: 216618 | C6: 15629 | D6: 24397 | E6: 18564 | F6: 14287 | G6: =SUM(B6:F6)
A7: Zeta | B7: 208584 | C7: 34692 | D7: 32932 | E7: 24883 | F7: 10075 | G7: =SUM(B7:F7)
A8: Eta | B8: 91402 | C8: 39910 | D8: 51636 | E8: 25306 | F8: 8874 | G8: =SUM(B8:F8)
A9: Theta | B9: 239290 | C9: 30852 | D9: 45421 | E9: 17827 | F9: 19670 | G9: =SUM(B9:F9)
A10: Iota | B10: 242619 | C10: 32551 | D10: 30503 | E10: 35982 | F10: 11638 | G10: =SUM(B10:F10)
A11: Kappa | B11: 242805 | C11: 23254 | D11: 32852 | E11: 42170 | F11: 15748 | G11: =SUM(B11:F11)
A13: NEXT YEAR OPEX
A14: Alpha | G14: =G2*(1+OM_EscalationRate)
A15: Beta | G15: =G3*(1+OM_EscalationRate)
A16: Gamma | G16: =G4*(1+Gamma_EscalationCap)
A17: Delta | G17: =G5*(1+OM_EscalationRate)
A18: Epsilon | G18: =G6*(1+OM_EscalationRate)
A19: Zeta | G19: =G7*(1+OM_EscalationRate)
A20: Eta | G20: =G8*(1+OM_EscalationRate)
A21: Theta | G21: =G9*(1+OM_EscalationRate)
A22: Iota | G22: =G10*(1+OM_EscalationRate)
A23: Kappa | G23: =G11*(1+OM_EscalationRate)
